ameck_copilot/__init__.py
ameck_copilot/cli.py
ameck_copilot/app/__init__.py
ameck_copilot/app/config.py
ameck_copilot/app/main.py
ameck_copilot/app/models.py
ameck_copilot/app/routes/__init__.py
ameck_copilot/app/routes/chat.py
ameck_copilot/app/services/__init__.py
ameck_copilot/app/services/claude_service.py
ameck_copilot/app/services/groq_service.py
ameck_copilot/static/index.html
ameck_copilot/static/css/styles.css
ameck_copilot/static/js/app.js
ameck_copilot/tests/test_api_modes.py
ameck_copilot/tests/test_modes.py
ameck_copilot/tests/test_plan_parsing.py
ameck_copilot-1.0.1.dist-info/licenses/LICENSE
ameck_copilot-1.0.1.dist-info/METADATA
ameck_copilot-1.0.1.dist-info/WHEEL
ameck_copilot-1.0.1.dist-info/entry_points.txt
ameck_copilot-1.0.1.dist-info/top_level.txt
ameck_copilot-1.0.1.dist-info/RECORD
