Metadata-Version: 2.4
Name: ameck-copilot
Version: 1.0.1
Summary: AI-powered coding assistant with a beautiful web interface, powered by free Groq API
Author-email: Ameck <ameck@example.com>
License-Expression: MIT
Project-URL: Homepage, https://github.com/QuantBender/ameck-copilot
Project-URL: Repository, https://github.com/QuantBender/ameck-copilot
Project-URL: Documentation, https://github.com/QuantBender/ameck-copilot#readme
Project-URL: Issues, https://github.com/QuantBender/ameck-copilot/issues
Keywords: ai,copilot,coding-assistant,groq,llama,chatbot
Classifier: Development Status :: 4 - Beta
Classifier: Environment :: Web Environment
Classifier: Framework :: FastAPI
Classifier: Intended Audience :: Developers
Classifier: Operating System :: OS Independent
Classifier: Programming Language :: Python :: 3
Classifier: Programming Language :: Python :: 3.10
Classifier: Programming Language :: Python :: 3.11
Classifier: Programming Language :: Python :: 3.12
Classifier: Programming Language :: Python :: 3.13
Classifier: Topic :: Software Development :: Code Generators
Classifier: Topic :: Scientific/Engineering :: Artificial Intelligence
Requires-Python: >=3.10
License-File: LICENSE
Requires-Dist: fastapi>=0.115.0
Requires-Dist: uvicorn[standard]>=0.30.0
Requires-Dist: python-dotenv>=1.0.0
Requires-Dist: pydantic>=2.10.0
Requires-Dist: pydantic-settings>=2.6.0
Requires-Dist: groq>=0.9.0
Requires-Dist: websockets>=12.0
Requires-Dist: python-multipart>=0.0.6
Requires-Dist: httpx>=0.27.0
Requires-Dist: pygments>=2.17.2
Requires-Dist: rich>=13.0.0
Dynamic: license-file
